supergit/supergit.py
supergit-0.1.0.dist-info/LICENSE
supergit-0.1.0.dist-info/METADATA
supergit-0.1.0.dist-info/WHEEL
supergit-0.1.0.dist-info/entry_points.txt
supergit-0.1.0.dist-info/top_level.txt
supergit-0.1.0.dist-info/RECORD
