Metadata-Version: 2.1
Name: supergit
Version: 0.1.0
Summary: An intelligent file organiser
Author-email: Anubhab Chakraborty <anuv@akcanuv.com>
License: MIT
Project-URL: homepage, https://github.com/akcanuv/supergit
Classifier: Programming Language :: Python :: 3
Classifier: License :: OSI Approved :: MIT License
Classifier: Operating System :: OS Independent
Requires-Python: >=3.6
License-File: LICENSE
Requires-Dist: anthropic>=0.39.0
Requires-Dist: GitPython>=3.1.43
Requires-Dist: PyYAML>=6.0.2
